pylintqmd/__init__.py
pylintqmd/__main__.py
pylintqmd/args.py
pylintqmd/converter.py
pylintqmd-0.2.0.dist-info/entry_points.txt
pylintqmd-0.2.0.dist-info/licenses/LICENSE
pylintqmd-0.2.0.dist-info/WHEEL
pylintqmd-0.2.0.dist-info/METADATA
pylintqmd-0.2.0.dist-info/RECORD
