Metadata-Version: 2.4
Name: pylintqmd
Version: 0.2.0
Summary: pylintqmd
Author: Amy Heather
Classifier: License :: OSI Approved :: MIT License
License-File: LICENSE
Requires-Dist: pylint
Requires-Dist: pytest ; extra == "test"
Project-URL: Home, https://github.com/amyheather/pylintqmd
Provides-Extra: test
